pyTSEB/MO_similarity.py
pyTSEB/PyTSEB.py
pyTSEB/TSEB.py
pyTSEB/TSEBConfigFileInterface.py
pyTSEB/TSEBIPythonInterface.py
pyTSEB/__init__.py
pyTSEB/clumping_index.py
pyTSEB/dis_TSEB.py
pyTSEB/energy_combination_ET.py
pyTSEB/meteo_utils.py
pyTSEB/net_radiation.py
pyTSEB/physiology.py
pyTSEB/resistances.py
pyTSEB/wind_profile.py
pytseb-2.1.0.dist-info/licenses/LICENSE
pytseb-2.1.0.dist-info/METADATA
pytseb-2.1.0.dist-info/WHEEL
pytseb-2.1.0.dist-info/top_level.txt
pytseb-2.1.0.dist-info/RECORD
