Metadata-Version: 2.4
Name: pyTSEB
Version: 2.1.0
Summary: Two Source Energy Balance (TSEB) Models to estimate sensible and latent heat flux (evapotranspiration) from radiometric surface temperature data
Author-email: Héctor Nieto <hector.nieto@csic.es>, Radoslaw Guzinski <rmgu@dhigroup.com>, "Willam P. Kustas" <bill.kustas@usda.gov>
Maintainer-email: Héctor Nieto <hector.nieto@csic.es>, Radoslaw Guzinski <rmgu@dhigroup.com>
License-Expression: GPL-3.0-or-later
Project-URL: Homepage, https://github.com/hectornieto/pyTSEB
Project-URL: Documentation, https://pytseb.readthedocs.io
Keywords: TSEB,Two Source Energy Balance,Resistance Energy Balance,OSEB,One Source Energy Balance,DTD,Dual Time Differenced,Remote Sensing
Classifier: Development Status :: 5 - Production/Stable
Classifier: Intended Audience :: Science/Research
Classifier: Topic :: Scientific/Engineering :: Hydrology
Classifier: Topic :: Software Development :: Libraries :: Python Modules
Classifier: Programming Language :: Python
Classifier: Programming Language :: Python :: 3
Requires-Python: >=3.6
License-File: LICENSE
Requires-Dist: gdal>=3.8
Requires-Dist: numpy
Requires-Dist: scipy
Requires-Dist: pandas
Requires-Dist: jupyter
Requires-Dist: notebook
Requires-Dist: bokeh
Requires-Dist: netCDF4
Requires-Dist: Py6S
Requires-Dist: radiative-transfer-models
Dynamic: license-file
